ldapsm/__init__.py
ldapsm/__main__.py
ldapsm-1.0.0.dist-info/licenses/LICENSE
ldapsm-1.0.0.dist-info/METADATA
ldapsm-1.0.0.dist-info/WHEEL
ldapsm-1.0.0.dist-info/entry_points.txt
ldapsm-1.0.0.dist-info/top_level.txt
ldapsm-1.0.0.dist-info/RECORD
