Metadata-Version: 2.4
Name: ldapsm
Version: 1.0.0
Summary: CLI tool to manage OpenLDAP schema snippets under cn=config
Author: Kevin Veen-Birkenbach
License: MIT
Requires-Python: >=3.9
License-File: LICENSE
Requires-Dist: python-ldap>=3.4
Dynamic: license-file
